spsdk_pkcs11/__init__.py
spsdk_pkcs11/provider.py
spsdk_pkcs11/__pyinstaller/__init__.py
spsdk_pkcs11/__pyinstaller/hook-spsdk_pkcs11.py
spsdk_pkcs11-0.3.0.dist-info/LICENSE
spsdk_pkcs11-0.3.0.dist-info/METADATA
spsdk_pkcs11-0.3.0.dist-info/WHEEL
spsdk_pkcs11-0.3.0.dist-info/entry_points.txt
spsdk_pkcs11-0.3.0.dist-info/top_level.txt
spsdk_pkcs11-0.3.0.dist-info/RECORD
