Metadata-Version: 2.1
Name: spsdk-pkcs11
Version: 0.3.0
Summary: Signature Provider plugin for SPSDK using PKCS#11 interface
Author: NXP
Maintainer-email: Michal Starecek <michal.starecek@nxp.com>
License: BSD-3-Clause
Project-URL: Homepage, https://github.com/nxp-mcuxpresso/spsdk_plugins/tree/master/pkcs11
Project-URL: Issues, https://github.com/nxp-mcuxpresso/spsdk_plugins/issues
Keywords: NXP,SPSDK,pkcs11
Classifier: Development Status :: 2 - Pre-Alpha
Classifier: Intended Audience :: Developers
Classifier: License :: OSI Approved :: BSD License
Classifier: Natural Language :: English
Classifier: Programming Language :: Python :: 3
Classifier: Programming Language :: Python :: 3.9
Classifier: Programming Language :: Python :: 3.10
Classifier: Programming Language :: Python :: 3.11
Requires-Python: >=3.9
License-File: LICENSE
Requires-Dist: python-pkcs11
Requires-Dist: cached-property
